autocv/__init__.py
autocv/crossref.py
autocv/csv.py
autocv/latex.py
autocv/orcid.py
autocv/publication.py
autocv/pubmed.py
autocv/researcher.py
autocv/utils.py
autocv/vita.py
autocv/templates/autocv_template.tex
autocv/templates/back.tex
autocv/templates/front.tex
autocv/testdata/additional_pubs.csv
autocv/testdata/autocv_template.aux
autocv/testdata/autocv_template.log
autocv/testdata/autocv_template.out
autocv/testdata/autocv_template.pdf
autocv/testdata/autocv_template.tex
autocv/testdata/conference.csv
autocv/testdata/distinctions.tex
autocv/testdata/editorial.csv
autocv/testdata/editorial.tex
autocv/testdata/education.tex
autocv/testdata/employment.tex
autocv/testdata/funding.csv
autocv/testdata/funding.tex
autocv/testdata/header.tex
autocv/testdata/links.csv
autocv/testdata/memberships.tex
autocv/testdata/params.json
autocv/testdata/patents.tex
autocv/testdata/presentations.tex
autocv/testdata/pubs.tex
autocv/testdata/scholar.log
autocv/testdata/service.tex
autocv/testdata/talks.csv
autocv/testdata/talks.tex
autocv/testdata/teaching.csv
autocv/testdata/teaching.tex
autocv-1.3.3.data/scripts/autoCV
autocv-1.3.3.data/scripts/get_NSF_collaborators
autocv-1.3.3.dist-info/LICENSE
autocv-1.3.3.dist-info/METADATA
autocv-1.3.3.dist-info/WHEEL
autocv-1.3.3.dist-info/top_level.txt
autocv-1.3.3.dist-info/RECORD
