Metadata-Version: 2.1
Name: autocv
Version: 1.3.3
Summary: autoCV: An automated CV generator
Home-page: https://github.com/poldrack/autoCV
Download-URL: https://github.com/poldrack/autoCV
Maintainer: Russ Poldrack
Maintainer-email: poldrack@stanford.edu
License: MIT
Platform: UNKNOWN
Classifier: Intended Audience :: Science/Research
Classifier: Programming Language :: Python :: 3.6
Classifier: License :: OSI Approved :: BSD License
Classifier: Operating System :: POSIX
Classifier: Operating System :: Unix
Classifier: Operating System :: MacOS
License-File: LICENSE
Requires-Dist: pandas
Requires-Dist: numpy
Requires-Dist: Bio
Requires-Dist: requests
Requires-Dist: crossrefapi
Requires-Dist: scholarly
Requires-Dist: pypatent
Requires-Dist: pytest
